strands_perplexity/__init__.py
strands_perplexity/tool.py
strands_perplexity-0.1.0.dist-info/METADATA
strands_perplexity-0.1.0.dist-info/WHEEL
strands_perplexity-0.1.0.dist-info/licenses/LICENSE
strands_perplexity-0.1.0.dist-info/RECORD
