Metadata-Version: 2.4
Name: strands-perplexity
Version: 0.1.0
Summary: Perplexity Search API tool for Strands Agents - enables real-time web search with citations
Project-URL: Homepage, https://github.com/mkmeral/strands-perplexity
Project-URL: Documentation, https://github.com/mkmeral/strands-perplexity#readme
Project-URL: Repository, https://github.com/mkmeral/strands-perplexity
Project-URL: Issues, https://github.com/mkmeral/strands-perplexity/issues
Author-email: Murat Kaan Meral <muratkaanmeral@gmail.com>
License: Apache-2.0
License-File: LICENSE
Keywords: agents,ai,citations,perplexity,search,strands,tool,web-search
Classifier: Development Status :: 4 - Beta
Classifier: Intended Audience :: Developers
Classifier: License :: OSI Approved :: Apache Software License
Classifier: Programming Language :: Python :: 3
Classifier: Programming Language :: Python :: 3.10
Classifier: Programming Language :: Python :: 3.11
Classifier: Programming Language :: Python :: 3.12
Classifier: Programming Language :: Python :: 3.13
Classifier: Topic :: Internet :: WWW/HTTP :: Indexing/Search
Classifier: Topic :: Scientific/Engineering :: Artificial Intelligence
Requires-Python: >=3.10
Requires-Dist: httpx>=0.24.0
Requires-Dist: strands-agents>=1.0.0
Provides-Extra: dev
Requires-Dist: hatch; extra == 'dev'
Requires-Dist: mypy<1.0.0,>=0.981; extra == 'dev'
Requires-Dist: pytest-asyncio>=0.23.0; extra == 'dev'
Requires-Dist: pytest<9.0.0,>=8.0.0; extra == 'dev'
Requires-Dist: respx>=0.20.0; extra == 'dev'
Requires-Dist: ruff<0.14.0,>=0.13.0; extra == 'dev'
